jr_tools/__init__.py
jr_tools/cli.py
jr_tools/client.py
jr_tools/exceptions.py
jr_tools/jr_tools.py
jr_tools-0.3.1.dist-info/AUTHORS.rst
jr_tools-0.3.1.dist-info/LICENSE
jr_tools-0.3.1.dist-info/METADATA
jr_tools-0.3.1.dist-info/WHEEL
jr_tools-0.3.1.dist-info/entry_points.txt
jr_tools-0.3.1.dist-info/top_level.txt
jr_tools-0.3.1.dist-info/RECORD
