Metadata-Version: 2.1
Name: jr-tools
Version: 0.3.1
Summary: A collection of tools to handle Jasper Reports with python
Home-page: https://github.com/erickgnavar/jr_tools
Author: Erick Navarro
Author-email: erick@navarro.io
License: MIT license
Keywords: jr_tools
Platform: UNKNOWN
Classifier: Development Status :: 2 - Pre-Alpha
Classifier: Intended Audience :: Developers
Classifier: License :: OSI Approved :: MIT License
Classifier: Natural Language :: English
Classifier: Programming Language :: Python :: 2
Classifier: Programming Language :: Python :: 2.7
Classifier: Programming Language :: Python :: 3
Classifier: Programming Language :: Python :: 3.3
Classifier: Programming Language :: Python :: 3.4
Classifier: Programming Language :: Python :: 3.5
Requires-Dist: Click (<7.0,>=6.0)
Requires-Dist: requests (>=2.18)
Requires-Dist: PyYAML (>=3.12)
